{
  "Memory Report": {
    "Name": "mct_quantized_model",
    "Runtime Memory Physical Size": "1.60MB",
    "Model Memory Physical Size": "3.51MB",
    "Reserved Memory": "1.00KB",
    "Memory Usage": "5.11MB",
    "Total Memory Available On Chip": "8.00MB",
    "Memory Utilization": "64%",
    "Fit In Chip": true,
    "Input Persistent": true,
    "Networks": [
      {
        "Hash": "mct_quantized_model",
        "Name": "mct_quantized_model",
        "Runtime Memory Physical Size": "1.60MB",
        "Model Memory Physical Size": "3.51MB",
        "Input Persistence Cost": "151.00KB"
      }
    ]
  }
}